{
  "games": [
    {
      "id": "G-DB-18",
      "npbjp": {
        "url": "https://npb.jp/scores/2020/1008/g-db-18/index.html",
        "status": "（東京ドーム）\n                    3回裏",
        "attempts": []
      },
      "yahoo": {
        "url": "https://baseball.yahoo.co.jp/npb/game/2020100801/text",
        "attempts": [
          {
            "date": "2020-10-08",
            "url": "https://baseball.yahoo.co.jp/npb/game/2020100801/text",
            "title": "10月8日（木） 巨人 vs. ＤｅＮＡ 18回戦",
            "home": "G",
            "road": "DB",
            "gameNo": "18",
            "inning": "b4",
            "batter": "松原 聖弥｜1600070",
            "state": "無死1塁",
            "text": "一塁走者 〔増田大｜1500054〕 :盗塁成功 2塁",
            "pitcher": "三上｜1300037",
            "catcher": "戸柱｜1500064",
            "credit": 1,
            "sb": "SB",
            "cs": "",
            "runners": [
              "増田大｜1500054"
            ],
            "base": 2,
            "outs": 0,
            "RoB": "1--"
          }
        ],
        "status": false
      }
    },
    {
      "id": "C-T-20",
      "npbjp": {
        "url": "https://npb.jp/scores/2020/1008/c-t-20/index.html",
        "status": "（マツダスタジアム）\n                    5回裏",
        "attempts": [
          {
            "url": "https://npb.jp/scores/2020/1008/c-t-20/playbyplay.html",
            "date": "2020-10-08",
            "home": "C",
            "road": "T",
            "inning": "t5",
            "pitcher": "野村｜21425135",
            "catchers": [
              "會澤｜31135114"
            ],
            "batter": "北條｜11215137",
            "runners": [
              "近本｜71075138"
            ],
            "sb": "SB",
            "cs": "",
            "base": "2",
            "ds": "",
            "outs": "2",
            "RoB": "1--",
            "credit": "1",
            "text": "2アウト｜1塁｜｜｜（走者・〔近本｜71075138〕）二塁盗塁成功"
          }
        ]
      },
      "yahoo": {
        "url": "https://baseball.yahoo.co.jp/npb/game/2020100802/text",
        "attempts": [
          {
            "date": "2020-10-08",
            "url": "https://baseball.yahoo.co.jp/npb/game/2020100802/text",
            "title": "10月8日（木） 広島 vs. 阪神 20回戦",
            "home": "C",
            "road": "T",
            "gameNo": "20",
            "inning": "t5",
            "batter": "北條 史也｜1200063",
            "state": "二死1塁",
            "text": "一塁走者 〔近本｜1800065〕 :盗塁成功 2塁",
            "pitcher": "野村｜1100081",
            "catcher": "會澤｜700050",
            "credit": 1,
            "sb": "SB",
            "cs": "",
            "runners": [
              "近本｜1800065"
            ],
            "base": 2,
            "outs": 2,
            "RoB": "1--"
          }
        ],
        "status": false
      }
    },
    {
      "id": "F-E-21",
      "npbjp": {
        "url": "https://npb.jp/scores/2020/1008/f-e-21/index.html",
        "status": "（札幌ドーム）\n                    4回表",
        "attempts": []
      },
      "yahoo": {
        "url": "https://baseball.yahoo.co.jp/npb/game/2020100803/text",
        "attempts": [],
        "status": false
      }
    },
    {
      "id": "L-H-17",
      "npbjp": {
        "url": "https://npb.jp/scores/2020/1008/l-h-17/index.html",
        "status": "（メットライフ）\n                    4回裏",
        "attempts": [
          {
            "url": "https://npb.jp/scores/2020/1008/l-h-17/playbyplay.html",
            "date": "2020-10-08",
            "home": "L",
            "road": "H",
            "inning": "t2",
            "pitcher": "今井｜31335134",
            "catchers": [
              "森｜91495139"
            ],
            "batter": "中村晃｜11215116",
            "runners": [
              "周東｜21925136"
            ],
            "sb": "",
            "cs": "CS",
            "base": "2",
            "ds": "",
            "outs": "2",
            "RoB": "1-3",
            "credit": "1",
            "text": "2アウト｜1・3塁｜｜｜（走者・〔周東｜21925136〕）二塁盗塁失敗"
          }
        ]
      },
      "yahoo": {
        "url": "https://baseball.yahoo.co.jp/npb/game/2020100804/text",
        "attempts": [
          {
            "date": "2020-10-08",
            "url": "https://baseball.yahoo.co.jp/npb/game/2020100804/text",
            "title": "10月8日（木） 西武 vs. ソフトバンク 17回戦",
            "home": "L",
            "road": "H",
            "gameNo": "17",
            "inning": "t2",
            "batter": "中村 晃｜800081",
            "state": "二死1,3塁",
            "text": "一塁走者 〔周東｜1700135〕 :盗塁を試みるもアウト 3アウトチェンジ",
            "pitcher": "今井｜1600127",
            "catcher": "森｜1300100",
            "credit": 1,
            "sb": "",
            "cs": "CS",
            "runners": [
              "周東｜1700135"
            ],
            "base": 2,
            "outs": 2,
            "RoB": "1-3"
          }
        ],
        "status": false
      }
    }
  ],
  "numOfGames": 4
}