{
  "games": [
    {
      "id": "T-S-21",
      "npbjp": {
        "url": "https://npb.jp/scores/2020/1019/t-s-21/index.html",
        "status": "Final",
        "attempts": [
          {
            "url": "https://npb.jp/scores/2020/1019/t-s-21/playbyplay.html",
            "date": "2020-10-19",
            "home": "T",
            "road": "S",
            "inning": "b9",
            "pitcher": "石山｜21125137",
            "catchers": [
              "中村｜51255118"
            ],
            "batter": "ボーア｜63765151",
            "runners": [
              "植田｜01305130"
            ],
            "sb": "SB",
            "cs": "",
            "base": "2",
            "ds": "",
            "outs": "1",
            "RoB": "1--",
            "credit": "1",
            "text": "1アウト｜1塁｜｜｜（走者・〔植田｜01305130〕）二塁盗塁成功"
          }
        ]
      },
      "yahoo": {
        "url": "https://baseball.yahoo.co.jp/npb/game/2020101902/text",
        "attempts": [
          {
            "date": "2020-10-19",
            "url": "https://baseball.yahoo.co.jp/npb/game/2020101902/text",
            "title": "10月19日（月） 阪神 vs. ヤクルト 21回戦",
            "home": "T",
            "road": "S",
            "gameNo": "21",
            "inning": "b9",
            "batter": "ボーア｜1900142",
            "state": "一死1塁",
            "text": "空振り三振に倒れるもスタートを切っていた一塁走者 〔植田｜1400172〕 が盗塁成功 2アウト2塁",
            "pitcher": "石山｜1200075",
            "catcher": "中村｜900044",
            "credit": 1,
            "sb": "SB",
            "cs": "",
            "runners": [
              "植田｜1400172"
            ],
            "base": 2,
            "outs": 1,
            "RoB": "1--"
          }
        ],
        "status": "Final"
      }
    }
  ],
  "numOfGames": 1
}