{
  "games": [
    {
      "id": "G-S-15",
      "npbjp": {
        "url": "https://npb.jp/scores/2020/0912/g-s-15/index.html",
        "status": "（東京ドーム）\n                    4回表",
        "attempts": [
          {
            "url": "https://npb.jp/scores/2020/0912/g-s-15/playbyplay.html",
            "date": "2020-09-12",
            "home": "G",
            "road": "S",
            "inning": "b1",
            "pitcher": "吉田大喜｜43145151",
            "catchers": [
              "西田｜41245133"
            ],
            "batter": "ウィーラー｜03105130",
            "runners": [
              "松原｜21825134"
            ],
            "sb": "SB",
            "cs": "",
            "base": "2",
            "ds": "",
            "outs": "1",
            "RoB": "1--",
            "credit": "1",
            "text": "1アウト｜1塁｜｜｜（走者・〔松原｜21825134〕）二塁盗塁成功"
          },
          {
            "url": "https://npb.jp/scores/2020/0912/g-s-15/playbyplay.html",
            "date": "2020-09-12",
            "home": "G",
            "road": "S",
            "inning": "b7",
            "pitcher": "近藤｜91795115",
            "catchers": [
              "西田｜41245133"
            ],
            "batter": "大城｜21325136",
            "runners": [
              "吉川大｜21825133"
            ],
            "sb": "SB",
            "cs": "",
            "base": "2",
            "ds": "",
            "outs": "2",
            "RoB": "1--",
            "credit": "1",
            "text": "2アウト｜1塁｜｜｜（走者・〔吉川大｜21825133〕）二塁盗塁成功"
          },
          {
            "url": "https://npb.jp/scores/2020/0912/g-s-15/playbyplay.html",
            "date": "2020-09-12",
            "home": "G",
            "road": "S",
            "inning": "b8",
            "pitcher": "長谷川｜11615134",
            "catchers": [
              "西田｜41245133"
            ],
            "batter": "岸田｜91595136",
            "runners": [
              "吉川尚｜73375134"
            ],
            "sb": "SB",
            "cs": "",
            "base": "2",
            "ds": "",
            "outs": "0",
            "RoB": "1--",
            "credit": "1",
            "text": "0アウト｜1塁｜｜｜（走者・〔吉川尚｜73375134〕）二塁盗塁成功"
          }
        ]
      },
      "yahoo": {
        "url": "https://baseball.yahoo.co.jp/npb/game/2020091201/text",
        "attempts": [
          {
            "date": "2020-09-12",
            "url": "https://baseball.yahoo.co.jp/npb/game/2020091201/text",
            "title": "9月12日（土） 巨人 vs. ヤクルト 15回戦",
            "home": "G",
            "road": "S",
            "gameNo": "15",
            "inning": "b1",
            "batter": "ウィーラー｜1500015",
            "state": "一死1塁",
            "text": "一塁走者 〔松原｜1600070〕 :すかさず初球から走って盗塁成功 2塁",
            "pitcher": "吉田大喜｜1900025",
            "catcher": "西田｜1000134",
            "credit": 1,
            "sb": "SB",
            "cs": "",
            "runners": [
              "松原｜1600070"
            ],
            "base": 2,
            "outs": 1,
            "RoB": "1--"
          },
          {
            "date": "2020-09-12",
            "url": "https://baseball.yahoo.co.jp/npb/game/2020091201/text",
            "title": "9月12日（土） 巨人 vs. ヤクルト 15回戦",
            "home": "G",
            "road": "S",
            "gameNo": "15",
            "inning": "b7",
            "batter": "大城 卓三｜1700044",
            "state": "二死1塁",
            "text": "一塁走者 〔吉川大｜1000139〕 :盗塁成功 2塁",
            "pitcher": "近藤｜12140",
            "catcher": "西田｜1000134",
            "credit": 1,
            "sb": "SB",
            "cs": "",
            "runners": [
              "吉川大｜1000139"
            ],
            "base": 2,
            "outs": 2,
            "RoB": "1--"
          },
          {
            "date": "2020-09-12",
            "url": "https://baseball.yahoo.co.jp/npb/game/2020091201/text",
            "title": "9月12日（土） 巨人 vs. ヤクルト 15回戦",
            "home": "G",
            "road": "S",
            "gameNo": "15",
            "inning": "b8",
            "batter": "岸田 行倫｜1700043",
            "state": "無死1塁",
            "text": "空振り三振に倒れるもスタートを切っていた一塁走者 〔吉川尚｜1600059〕 が盗塁成功 1アウト2塁",
            "pitcher": "長谷川｜1600169",
            "catcher": "西田｜1000134",
            "credit": 1,
            "sb": "SB",
            "cs": "",
            "runners": [
              "吉川尚｜1600059"
            ],
            "base": 2,
            "outs": 0,
            "RoB": "1--"
          }
        ],
        "status": "Final"
      }
    },
    {
      "id": "DB-D-14",
      "npbjp": {
        "url": "https://npb.jp/scores/2020/0912/db-d-14/index.html",
        "status": "Final",
        "attempts": []
      },
      "yahoo": {
        "url": "https://baseball.yahoo.co.jp/npb/game/2020091202/text",
        "attempts": [],
        "status": "Final"
      }
    },
    {
      "id": "T-C-16",
      "npbjp": {
        "url": "https://npb.jp/scores/2020/0912/t-c-16/index.html",
        "status": "Final",
        "attempts": []
      },
      "yahoo": {
        "url": "https://baseball.yahoo.co.jp/npb/game/2020091203/text",
        "attempts": [],
        "status": "Final"
      }
    },
    {
      "id": "H-L-13",
      "npbjp": {
        "url": "https://npb.jp/scores/2020/0912/h-l-13/index.html",
        "status": "Final",
        "attempts": [
          {
            "url": "https://npb.jp/scores/2020/0912/h-l-13/playbyplay.html",
            "date": "2020-09-12",
            "home": "H",
            "road": "L",
            "inning": "t7",
            "pitcher": "嘉弥真｜91595135",
            "catchers": [
              "髙谷｜41045114"
            ],
            "batter": "源田｜71775134",
            "runners": [
              "外崎｜41245130"
            ],
            "sb": "SB",
            "cs": "",
            "base": "2",
            "ds": "",
            "outs": "2",
            "RoB": "1--",
            "credit": "1",
            "text": "2アウト｜1塁｜｜｜（走者・〔外崎｜41245130〕）二塁盗塁成功"
          }
        ]
      },
      "yahoo": {
        "url": "https://baseball.yahoo.co.jp/npb/game/2020091206/text",
        "attempts": [
          {
            "date": "2020-09-12",
            "url": "https://baseball.yahoo.co.jp/npb/game/2020091206/text",
            "title": "9月12日（土） ソフトバンク vs. 西武 13回戦",
            "home": "H",
            "road": "L",
            "gameNo": "13",
            "inning": "t7",
            "batter": "源田 壮亮｜1600129",
            "state": "二死1塁",
            "text": "一塁走者 〔外崎｜1400184〕 :盗塁成功 2塁",
            "pitcher": "嘉弥真｜1100119",
            "catcher": "髙谷｜700099",
            "credit": 1,
            "sb": "SB",
            "cs": "",
            "runners": [
              "外崎｜1400184"
            ],
            "base": 2,
            "outs": 2,
            "RoB": "1--"
          }
        ],
        "status": "Final"
      }
    }
  ],
  "numOfGames": 4
}